sn74hcs137/__init__.py
sn74hcs137/driver.py
sn74hcs137/py.typed
sn74hcs137/tests/__init__.py
sn74hcs137-0.0.0.dev3.dist-info/LICENSE
sn74hcs137-0.0.0.dev3.dist-info/METADATA
sn74hcs137-0.0.0.dev3.dist-info/WHEEL
sn74hcs137-0.0.0.dev3.dist-info/top_level.txt
sn74hcs137-0.0.0.dev3.dist-info/RECORD
