Metadata-Version: 2.1
Name: sn74hcs137
Version: 0.0.0.dev3
Summary: A Python driver for Texas instruments SN74HCS137 3- to 8-Line Decoder/Demultiplexer with Address Latches and SchmittTrigger Inputs
Home-page: https://github.com/blueskysolarracing/sn74hcs137
Author: Blue Sky Solar Racing
Author-email: blueskysolar@studentorg.utoronto.ca
License: MIT
Project-URL: Documentation, https://sn74hcs137.readthedocs.io/en/latest/
Project-URL: Source, https://github.com/blueskysolarracing/sn74hcs137
Project-URL: Tracker, https://github.com/blueskysolarracing/sn74hcs137/issues
Keywords: python
Classifier: Development Status :: 5 - Production/Stable
Classifier: Intended Audience :: Developers
Classifier: Intended Audience :: Education
Classifier: Topic :: Education
Classifier: Topic :: Scientific/Engineering
Classifier: License :: OSI Approved :: MIT License
Classifier: Operating System :: OS Independent
Classifier: Programming Language :: Python
Classifier: Programming Language :: Python :: 3
Classifier: Programming Language :: Python :: 3 :: Only
Classifier: Programming Language :: Python :: 3.11
Classifier: Programming Language :: Python :: 3.12
Requires-Python: >=3.11
License-File: LICENSE
Requires-Dist: python-periphery <3,>=2.4.1
